hedju/__init__.py
hedju/pagination.py
hedju-0.1.0.dist-info/AUTHORS.rst
hedju-0.1.0.dist-info/LICENSE
hedju-0.1.0.dist-info/METADATA
hedju-0.1.0.dist-info/WHEEL
hedju-0.1.0.dist-info/top_level.txt
hedju-0.1.0.dist-info/RECORD
