Metadata-Version: 1.1
Name: hedju
Version: 0.1.0
Summary: Class implementing limit/offset pagination in headers with optional enveloping.
Home-page: https://github.com/sunscrapers/hedju
Author: Sunscrapers
Author-email: d.kozaczko@sunscrapers.com
License: MIT license
Keywords: hedju
Platform: UNKNOWN
Classifier: Development Status :: 2 - Pre-Alpha
Classifier: Intended Audience :: Developers
Classifier: License :: OSI Approved :: MIT License
Classifier: Natural Language :: English
Classifier: Programming Language :: Python :: 3
Classifier: Programming Language :: Python :: 3.5
Classifier: Programming Language :: Python :: 3.6
Classifier: Programming Language :: Python :: 3.7
